hackerhelp.py
hackerhelp-0.1.dist-info/METADATA
hackerhelp-0.1.dist-info/WHEEL
hackerhelp-0.1.dist-info/entry_points.txt
hackerhelp-0.1.dist-info/top_level.txt
hackerhelp-0.1.dist-info/RECORD
