Metadata-Version: 2.1
Name: hackerhelp
Version: 0.1
Summary: A tool to help hackers
Home-page: https://github.com/AIMadeScripts/reminder
Author: Mr. Robot
Author-email: alertsontwitter@gmail.com
Classifier: Programming Language :: Python :: 3
Classifier: License :: OSI Approved :: MIT License
Classifier: Operating System :: OS Independent
